[
  {
    "id": 1,
    "title": "Lesson 1",
    "description": "Practice the sequence asdfg",
    "level": "beginner",
    "targetKeys": ["a", "s", "d", "f", "g"],
    "text": "asdfg",
    "minPPM": 15,
    "minAccuracy": 85,
    "repetitionCount": 50
  },
  {
    "id": 2,
    "title": "Lesson 2",
    "description": "Practice the sequence gfdsa",
    "level": "beginner",
    "targetKeys": ["a", "s", "d", "f", "g"],
    "text": "gfdsa",
    "minPPM": 15,
    "minAccuracy": 85,
    "repetitionCount": 50
  },
  {
    "id": 3,
    "title": "Lesson 3",
    "description": "Practice the sequence asdgf",
    "level": "beginner",
    "targetKeys": ["a", "s", "d", "f", "g"],
    "text": "asdgf",
    "minPPM": 15,
    "minAccuracy": 85,
    "repetitionCount": 50
  },
  {
    "id": 4,
    "title": "Lesson 4",
    "description": "Practice the sequence afsdg",
    "level": "beginner",
    "targetKeys": ["a", "s", "d", "f", "g"],
    "text": "afsdg",
    "minPPM": 15,
    "minAccuracy": 85,
    "repetitionCount": 50
  },
  {
    "id": 5,
    "title": "Lesson 5",
    "description": "Practice the sequence safdg",
    "level": "beginner",
    "targetKeys": ["a", "s", "d", "f", "g"],
    "text": "safdg",
    "minPPM": 15,
    "minAccuracy": 85,
    "repetitionCount": 50
  },
  {
    "id": 6,
    "title": "Lesson 6",
    "description": "Practice the sequence ;lkjh",
    "level": "beginner",
    "targetKeys": [";", "l", "k", "j", "h"],
    "text": ";lkjh",
    "minPPM": 15,
    "minAccuracy": 85,
    "repetitionCount": 50
  },
  {
    "id": 7,
    "title": "Lesson 7",
    "description": "Practice the sequence hjkl;",
    "level": "beginner",
    "targetKeys": [";", "l", "k", "j", "h"],
    "text": "hjkl;",
    "minPPM": 15,
    "minAccuracy": 85,
    "repetitionCount": 50
  },
  {
    "id": 8,
    "title": "Lesson 8",
    "description": "Practice the sequence ;ljkh",
    "level": "beginner",
    "targetKeys": [";", "l", "k", "j", "h"],
    "text": ";ljkh",
    "minPPM": 15,
    "minAccuracy": 85,
    "repetitionCount": 50
  },
  {
    "id": 9,
    "title": "Lesson 9",
    "description": "Practice the sequence l;kjh",
    "level": "beginner",
    "targetKeys": [";", "l", "k", "j", "h"],
    "text": "l;kjh",
    "minPPM": 15,
    "minAccuracy": 85,
    "repetitionCount": 50
  },
  {
    "id": 10,
    "title": "Lesson 10",
    "description": "Practice the sequence k;ljh",
    "level": "beginner",
    "targetKeys": [";", "l", "k", "j", "h"],
    "text": "k;ljh",
    "minPPM": 15,
    "minAccuracy": 85,
    "repetitionCount": 50
  },
  {
    "id": 11,
    "title": "Lesson 11",
    "description": "Practice the sequence zxcvb",
    "level": "beginner",
    "targetKeys": ["z", "x", "c", "v", "b"],
    "text": "zxcvb",
    "minPPM": 15,
    "minAccuracy": 85,
    "repetitionCount": 50
  },
  {
    "id": 12,
    "title": "Lesson 12",
    "description": "Practice the sequence bvcxz",
    "level": "beginner",
    "targetKeys": ["z", "x", "c", "v", "b"],
    "text": "bvcxz",
    "minPPM": 15,
    "minAccuracy": 85,
    "repetitionCount": 50
  },
  {
    "id": 13,
    "title": "Lesson 13",
    "description": "Practice the sequence zxvcb",
    "level": "beginner",
    "targetKeys": ["z", "x", "c", "v", "b"],
    "text": "zxvcb",
    "minPPM": 15,
    "minAccuracy": 85,
    "repetitionCount": 50
  },
  {
    "id": 14,
    "title": "Lesson 14",
    "description": "Practice the sequence xzcvb",
    "level": "beginner",
    "targetKeys": ["z", "x", "c", "v", "b"],
    "text": "xzcvb",
    "minPPM": 15,
    "minAccuracy": 85,
    "repetitionCount": 50
  },
  {
    "id": 15,
    "title": "Lesson 15",
    "description": "Practice the sequence czxvb",
    "level": "beginner",
    "targetKeys": ["z", "x", "c", "v", "b"],
    "text": "czxvb",
    "minPPM": 15,
    "minAccuracy": 85,
    "repetitionCount": 50
  },
  {
    "id": 16,
    "title": "Lesson 16",
    "description": "Practice the sequence /.,mn",
    "level": "beginner",
    "targetKeys": ["/", ".", ",", "m", "n"],
    "text": "/.,mn",
    "minPPM": 15,
    "minAccuracy": 85,
    "repetitionCount": 50
  },
  {
    "id": 17,
    "title": "Lesson 17",
    "description": "Practice the sequence nm,./",
    "level": "beginner",
    "targetKeys": ["/", ".", ",", "m", "n"],
    "text": "nm,./",
    "minPPM": 15,
    "minAccuracy": 85,
    "repetitionCount": 50
  },
  {
    "id": 18,
    "title": "Lesson 18",
    "description": "Practice the sequence /,.nm",
    "level": "beginner",
    "targetKeys": ["/", ".", ",", "m", "n"],
    "text": "/,.nm",
    "minPPM": 15,
    "minAccuracy": 85,
    "repetitionCount": 50
  },
  {
    "id": 19,
    "title": "Lesson 19",
    "description": "Practice the sequence .,/mn",
    "level": "beginner",
    "targetKeys": ["/", ".", ",", "m", "n"],
    "text": ".,/mn",
    "minPPM": 15,
    "minAccuracy": 85,
    "repetitionCount": 50
  },
  {
    "id": 20,
    "title": "Lesson 20",
    "description": "Practice the sequence m/,.n",
    "level": "beginner",
    "targetKeys": ["/", ".", ",", "m", "n"],
    "text": "m/,.n",
    "minPPM": 15,
    "minAccuracy": 85,
    "repetitionCount": 50
  },
  {
    "id": 21,
    "title": "Lesson 21",
    "description": "Practice the sequence qwert",
    "level": "beginner",
    "targetKeys": ["q", "w", "e", "r", "t"],
    "text": "qwert",
    "minPPM": 15,
    "minAccuracy": 85,
    "repetitionCount": 50
  },
  {
    "id": 22,
    "title": "Lesson 22",
    "description": "Practice the sequence trewq",
    "level": "beginner",
    "targetKeys": ["q", "w", "e", "r", "t"],
    "text": "trewq",
    "minPPM": 15,
    "minAccuracy": 85,
    "repetitionCount": 50
  },
  {
    "id": 23,
    "title": "Lesson 23",
    "description": "Practice the sequence qwrte",
    "level": "beginner",
    "targetKeys": ["q", "w", "e", "r", "t"],
    "text": "qwrte",
    "minPPM": 15,
    "minAccuracy": 85,
    "repetitionCount": 50
  },
  {
    "id": 24,
    "title": "Lesson 24",
    "description": "Practice the sequence wqert",
    "level": "beginner",
    "targetKeys": ["q", "w", "e", "r", "t"],
    "text": "wqert",
    "minPPM": 15,
    "minAccuracy": 85,
    "repetitionCount": 50
  },
  {
    "id": 25,
    "title": "Lesson 25",
    "description": "Practice the sequence eqwrt",
    "level": "beginner",
    "targetKeys": ["q", "w", "e", "r", "t"],
    "text": "eqwrt",
    "minPPM": 15,
    "minAccuracy": 85,
    "repetitionCount": 50
  },
  {
    "id": 26,
    "title": "Lesson 26",
    "description": "Practice the sequence poiuy",
    "level": "beginner",
    "targetKeys": ["p", "o", "i", "u", "y"],
    "text": "poiuy",
    "minPPM": 15,
    "minAccuracy": 85,
    "repetitionCount": 50
  },
  {
    "id": 27,
    "title": "Lesson 27",
    "description": "Practice the sequence yuiop",
    "level": "beginner",
    "targetKeys": ["p", "o", "i", "u", "y"],
    "text": "yuiop",
    "minPPM": 15,
    "minAccuracy": 85,
    "repetitionCount": 50
  },
  {
    "id": 28,
    "title": "Lesson 28",
    "description": "Practice the sequence pouiy",
    "level": "beginner",
    "targetKeys": ["p", "o", "i", "u", "y"],
    "text": "pouiy",
    "minPPM": 15,
    "minAccuracy": 85,
    "repetitionCount": 50
  },
  {
    "id": 29,
    "title": "Lesson 29",
    "description": "Practice the sequence opuiy",
    "level": "beginner",
    "targetKeys": ["p", "o", "i", "u", "y"],
    "text": "opuiy",
    "minPPM": 15,
    "minAccuracy": 85,
    "repetitionCount": 50
  },
  {
    "id": 30,
    "title": "Lesson 30",
    "description": "Practice the sequence ipouy",
    "level": "beginner",
    "targetKeys": ["p", "o", "i", "u", "y"],
    "text": "ipouy",
    "minPPM": 15,
    "minAccuracy": 85,
    "repetitionCount": 50
  },
  {
    "id": 34,
    "title": "Lesson 34: Bottom Row",
    "description": "Learn: Z, X, C, V, B, N, M",
    "level": "intermediate",
    "targetKeys": ["z", "x", "c", "v", "b", "n", "m"],
    "text": "zzz xxx ccc vvv bbb nnn mmm zxcv bnm zxcvbnm vbnmzxc zxbn vcnm",
    "minPPM": 20,
    "minAccuracy": 85
  },
  {
    "id": 35,
    "title": "Lesson 35: Complete Alphabet",
    "description": "Practice with all letters",
    "level": "intermediate",
    "targetKeys": ["a", "b", "c", "d", "e", "f", "g", "h", "i", "j", "k", "l", "m", "n", "o", "p", "q", "r", "s", "t", "u", "v", "w", "x", "y", "z"],
    "text": "home table love life time world form part make great tell stay",
    "minPPM": 30,
    "minAccuracy": 90
  },
  {
    "id": 36,
    "title": "Lesson 36: Common Words",
    "description": "Type frequent English words",
    "level": "intermediate",
    "targetKeys": [],
    "text": "the that have from this will with they what been when make than into time other only over also back after work first well",
    "minPPM": 35,
    "minAccuracy": 90
  },
  {
    "id": 37,
    "title": "Lesson 37: Numbers",
    "description": "Learn the number row: 1-0",
    "level": "intermediate",
    "targetKeys": ["1", "2", "3", "4", "5", "6", "7", "8", "9", "0"],
    "text": "111 222 333 444 555 666 777 888 999 000 123 456 789 012 345 678 901",
    "minPPM": 25,
    "minAccuracy": 88
  },
  {
    "id": 38,
    "title": "Lesson 38: Basic Punctuation",
    "description": "Practice comma, period and space",
    "level": "intermediate",
    "targetKeys": [",", ".", " "],
    "text": "Hello, world. Today is a good day. Let's practice, always. Practice is important. Keep going, you can do it.",
    "minPPM": 30,
    "minAccuracy": 90
  },
  {
    "id": 39,
    "title": "Lesson 39: Simple Sentences",
    "description": "Type complete sentences with punctuation",
    "level": "advanced",
    "targetKeys": [],
    "text": "Constant practice is the secret to success. The more you train, the better you get. Fast typing helps a lot at work.",
    "minPPM": 40,
    "minAccuracy": 92
  },
  {
    "id": 40,
    "title": "Lesson 40: Narrative Text",
    "description": "Practice with flowing text",
    "level": "advanced",
    "targetKeys": [],
    "text": "Once upon a time there was a young person who wanted to learn to type very fast. They practiced every day, never giving up. Over time, their fingers began to fly over the keyboard.",
    "minPPM": 45,
    "minAccuracy": 93
  },
  {
    "id": 41,
    "title": "Lesson 41: Special Characters",
    "description": "Learn special symbols: @#$%&*",
    "level": "advanced",
    "targetKeys": ["@", "#", "$", "%", "&", "*", "(", ")", "-", "_", "+", "="],
    "text": "email@example.com #hashtag $100.00 50% discount & you too! (*important) test_file full-name 2+2=4",
    "minPPM": 35,
    "minAccuracy": 90
  },
  {
    "id": 42,
    "title": "Lesson 42: Programming Code",
    "description": "Type code with real syntax",
    "level": "expert",
    "targetKeys": [],
    "text": "function calculate(a, b) { return a + b; } const result = calculate(10, 20); console.log(result);",
    "minPPM": 40,
    "minAccuracy": 92
  },
  {
    "id": 43,
    "title": "Lesson 43: Technical Text",
    "description": "Practice technical terminology",
    "level": "expert",
    "targetKeys": [],
    "text": "Microservices architecture enables horizontal scalability. The HTTP protocol uses REST requests. The algorithm performance is O(n log n).",
    "minPPM": 45,
    "minAccuracy": 93
  },
  {
    "id": 44,
    "title": "Lesson 44: Maximum Speed",
    "description": "Final speed challenge",
    "level": "expert",
    "targetKeys": [],
    "text": "The rapid development of modern technology constantly transforms our society. Qualified professionals need to quickly adapt to changes to remain relevant in the competitive market.",
    "minPPM": 50,
    "minAccuracy": 95
  },
  {
    "id": 45,
    "title": "Lesson 45: Maximum Precision",
    "description": "Focus on accuracy without errors",
    "level": "expert",
    "targetKeys": [],
    "text": "Excellence in typing comes not only from speed, but mainly from consistency and precision. Each correctly pressed key is a step towards mastery.",
    "minPPM": 50,
    "minAccuracy": 98
  },
  {
    "id": 46,
    "title": "Lesson 46: Master Challenge",
    "description": "Complete final test",
    "level": "expert",
    "targetKeys": [],
    "text": "Congratulations on making it this far! You have mastered the art of typing. Now it's time to apply your skills in the real world. Keep practicing and you will be unbeatable. Success!",
    "minPPM": 55,
    "minAccuracy": 98
  }
]
